{
  "name": "Eunice Mills",
  "age": 42,
  "address": {
    "street": "Lavbep Center",
    "city": "Jinkava",
    "state": "KY",
    "zip": "78950"
  },
  "contact": {
    "phone": "(981) 206-8902",
    "servicePhone": "800286756"
  },
  "birthday": "2001-12-04T05:11:16.632Z",
  "ip": "143.67.2.1",
  "foo": "bar",
  "profile": {
    "about": "Kav veliwkek gi fanfug dit eploh fokep copom adnidav aktab ziju eme je fot kurasooki kap didgus. Rehopame lufboh korci woselda okurenob ir tosatife iguroj ca sikko pasnale isim ob jeaditud corjoflu. Okuto new mub hupca hodooj zino akwele widmavci asu cenawu di dalu bi bal. Secul mohuzunet dub ejobefit luz uvuvuffe mig midtur lausolel edoek enazuno cop mi.",
    "bio": "Be rujo ge mi wucebu logoima cu jurrub geva kecma logugpu fubce cimceivu vaja. Famek lun ris bini wiheuzo saun lu gicanmu ir arolalma ogcesir uwove fej nuzeb olte. Tibu jacidu wuc re tobureze iwavuhna miidva riwawiv wokwut agokin sizak rarkisah dotlip ak. Lidloku ge acimupiz iptifut fo omi ozkom digefuf silfuta ope tebcifmej ja. Ta rul funasol acet bo kusi puuh rijumawo wur ne ite ubi ufo wam. Hanaw ku putco acoas najisozem rad ipihilti ola zov ris him cilmufeb zu."
  },
  "apiKey": "e4c609dc2a9ec1c40d03f4b6679e5e5c8fbe115153c722e4713c14ff4482fccb",
  "currency": {
    "code": "MYR",
    "name": "Malaysia Ringgit"
  }
}